BookerDownloadTool/__init__.py
BookerDownloadTool/__main__.py
BookerDownloadTool/bili.py
BookerDownloadTool/discuz.py
BookerDownloadTool/dl_gh_book.py
BookerDownloadTool/dmzj.py
BookerDownloadTool/freembook.py
BookerDownloadTool/lightnovel.py
BookerDownloadTool/links.py
BookerDownloadTool/medium.py
BookerDownloadTool/nhentai.py
BookerDownloadTool/stealth.min.js
BookerDownloadTool/uqer.py
BookerDownloadTool/util.py
BookerDownloadTool/webarchive.py
BookerDownloadTool/whole_site.py
BookerDownloadTool/wx.py
BookerDownloadTool/wx_external.py
BookerDownloadTool/yuque.py
BookerDownloadTool/yuque_external.py
BookerDownloadTool/zhihu_old.py
BookerDownloadTool/zhihu_ques.py
BookerDownloadTool/zhihu_ques_sele.py
BookerDownloadTool/zhihu_sele.py
BookerDownloadTool/zsxq.py
BookerDownloadTool-2023.8.30.0.dist-info/LICENSE
BookerDownloadTool-2023.8.30.0.dist-info/METADATA
BookerDownloadTool-2023.8.30.0.dist-info/WHEEL
BookerDownloadTool-2023.8.30.0.dist-info/entry_points.txt
BookerDownloadTool-2023.8.30.0.dist-info/top_level.txt
BookerDownloadTool-2023.8.30.0.dist-info/RECORD
